.env
.flags
.gitignore
MANIFEST.in
Procfile
Procfile_intp
Procfile_prod
README.md
env.sh
git-local.sh
procs-sagas-ai.md
procs_tests.py
sl_bot.py
sl_ent_vis.py
sl_parsers.py
sl_rulesets.py
sl_utils.py
startup.run
statemap.py
bots/agent_dispatcher/.flags
bots/agent_dispatcher/.gitignore
bots/agent_dispatcher/Procfile
bots/agent_dispatcher/Procfile_mod
bots/agent_dispatcher/README.md
bots/agent_dispatcher/__init__.py
bots/agent_dispatcher/config.yml
bots/agent_dispatcher/credentials.yml
bots/agent_dispatcher/domain.yml
bots/agent_dispatcher/endpoints.yml
bots/agent_dispatcher/env.sh
bots/agent_dispatcher/procs-agent-dispatcher.md
bots/agent_dispatcher/procs-bot-actions.ipynb
bots/agent_dispatcher/procs-dataset.ipynb
bots/agent_dispatcher/procs-nlu-integration.ipynb
bots/agent_dispatcher/procs-ruleset-kit.ipynb
bots/agent_dispatcher/startup.run
bots/agent_dispatcher/actions/__init__.py
bots/agent_dispatcher/actions/actions.py
bots/agent_dispatcher/assets/inspectors.json
bots/agent_dispatcher/assets/mod_es.json
bots/agent_dispatcher/assets/rs_common_de.yml
bots/agent_dispatcher/assets/rs_common_en.yml
bots/agent_dispatcher/assets/rs_common_id.yml
bots/agent_dispatcher/assets/rs_tests_ja.yml
bots/agent_dispatcher/data/nlu.md
bots/agent_dispatcher/data/nlu_avatar.md
bots/agent_dispatcher/data/stories.md
bots/agent_dispatcher/fixtures/.mark.md
bots/agent_dispatcher/fixtures/describes.md
bots/agent_dispatcher/fixtures/questions.md
bots/agent_dispatcher/fixtures/small_talk.md
bots/agent_dispatcher/inspectors/__init__.py
bots/agent_dispatcher/inspectors/cust_entity_inspector.py
bots/agent_dispatcher/rulesets/__init__.py
bots/agent_dispatcher/rulesets/rules_es.py
bots/agent_dispatcher/servants/__init__.py
bots/agent_dispatcher/servants/avatar_blueprints.py
bots/agent_dispatcher/servants/avatar_servant.py
bots/agent_dispatcher/servants/nlu_dispatcher.py
bots/agent_dispatcher/servants/nlu_mod.py
bots/genesis/.flags
bots/genesis/__init__.py
bots/genesis/config.yml
saai.egg-info/PKG-INFO
saai.egg-info/SOURCES.txt
saai.egg-info/dependency_links.txt
saai.egg-info/entry_points.txt
saai.egg-info/requires.txt
saai.egg-info/top_level.txt
saai-0.3.0.dist-info/METADATA
saai-0.3.0.dist-info/WHEEL
saai-0.3.0.dist-info/entry_points.txt
saai-0.3.0.dist-info/top_level.txt
saai-0.3.0.dist-info/RECORD
