Metadata-Version: 2.1
Name: saai
Version: 0.3.0
Summary: nlu components
Home-page: https://github.com/samlet/saai
Author: Samlet Wu
Author-email: xiaofei.wu@gmail.com
License: UNKNOWN
Project-URL: Bug Reports, https://github.com/samlet/saai/issues
Project-URL: Source, https://github.com/samlet/saai
Platform: UNKNOWN
Classifier: Programming Language :: Python :: 3
Classifier: License :: OSI Approved :: MIT License
Classifier: Operating System :: OS Independent
Requires-Python: >=3.6
Requires-Dist: jieba (~=0.40)
Requires-Dist: simplejson
Requires-Dist: paddlepaddle-tiny (~=1.6.1)
Requires-Dist: sagas (>=0.1.2)
Requires-Dist: python-json-config
Requires-Dist: python-dotenv
Provides-Extra: dev
Requires-Dist: jupyter (~=1.0.0) ; extra == 'dev'
Requires-Dist: streamlit (~=0.50.2) ; extra == 'dev'
Requires-Dist: ipymarkup (~=0.5.0) ; extra == 'dev'
Provides-Extra: rasa
Requires-Dist: rasa (~=1.6.0) ; extra == 'rasa'
Requires-Dist: rasa-sdk (~=1.6.0) ; extra == 'rasa'
